CryptMaster/CryptMaster.py
CryptMaster/Encrypt_Decrypt.py
CryptMaster/OpenApi.py
CryptMaster/SystemId.py
CryptMaster/__init__.py
CryptMaster-0.0.33.dist-info/LICENSE
CryptMaster-0.0.33.dist-info/METADATA
CryptMaster-0.0.33.dist-info/WHEEL
CryptMaster-0.0.33.dist-info/entry_points.txt
CryptMaster-0.0.33.dist-info/top_level.txt
CryptMaster-0.0.33.dist-info/RECORD
