Metadata-Version: 2.1
Name: CryptMaster
Version: 0.0.33
Summary: Startup Client for a Crypt Master Backend
Home-page: https://github.com/TheCryptMaster/CryptMaster
Author: Huth S0lo
Author-email: Huth S0lo <john@themorphium.io>
License: GNU GENERAL PUBLIC LICENSE
Project-URL: Homepage, https://github.com/TheCryptMaster/CryptMaster
Keywords: python,password,security,key server
Classifier: License :: OSI Approved :: GNU General Public License v3 or later (GPLv3+)
Classifier: Programming Language :: Python
Classifier: Programming Language :: Python :: 3
Requires-Python: >=3.9
License-File: LICENSE
Requires-Dist: pycryptodome ==3.20.0
Requires-Dist: httpx ==0.26.0
Requires-Dist: argon2-cffi ==23.1.0
Requires-Dist: platformdirs ==4.2.0
Requires-Dist: pypedreams ==0.0.1
Provides-Extra: dev
Requires-Dist: black ; extra == 'dev'
Requires-Dist: bumpver ; extra == 'dev'
Requires-Dist: isort ; extra == 'dev'
Requires-Dist: pip-tools ; extra == 'dev'
Requires-Dist: pytest ; extra == 'dev'
